SAcouS/__init__.py
SAcouS/acxfem/BCs_impose.py
SAcouS/acxfem/__init__.py
SAcouS/acxfem/assembly.py
SAcouS/acxfem/basis.py
SAcouS/acxfem/dofhandler.py
SAcouS/acxfem/materials.py
SAcouS/acxfem/mesh.py
SAcouS/acxfem/physic_assembler.py
SAcouS/acxfem/polynomial.py
SAcouS/acxfem/postprocess.py
SAcouS/acxfem/precompute_matrices.py
SAcouS/acxfem/precompute_matrices_lag.py
SAcouS/acxfem/quadratures.py
SAcouS/acxfem/solver.py
SAcouS/acxfem/utilities.py
SAcouS/acxmor/__init__.py
SAcouS/acxmor/modal_reduction.py
SAcouS/acxmor/myEIM.py
SAcouS/acxmor/myRBSolver.py
SAcouS/acxtmm/BC_matrix.py
SAcouS/acxtmm/__init__.py
SAcouS/acxtmm/adm_assembler.py
SAcouS/acxtmm/adm_basis.py
SAcouS/acxtmm/tmm.py
analytical/Biot_sol.py
analytical/Fluid_Biot_sol.py
analytical/__init__.py
analytical/fluid_sol.py
PyAcoustiX-1.0.0.dist-info/LICENSE
PyAcoustiX-1.0.0.dist-info/METADATA
PyAcoustiX-1.0.0.dist-info/WHEEL
PyAcoustiX-1.0.0.dist-info/top_level.txt
PyAcoustiX-1.0.0.dist-info/RECORD
