Metadata-Version: 2.1
Name: PyAcoustiX
Version: 1.0.0
Summary: A Python package for acoustic analysis
Home-page: https://github.com/Shaoqigit/PyXfem
Author: Shaoqi WU
Author-email: shaoqiwu@outlook.com
Classifier: Development Status :: 3 - Alpha
Classifier: Intended Audience :: Developers
Classifier: License :: OSI Approved :: MIT License
Classifier: Programming Language :: Python :: 3
Classifier: Programming Language :: Python :: 3.6
Classifier: Programming Language :: Python :: 3.7
Classifier: Programming Language :: Python :: 3.8
Requires-Python: >=3.8
License-File: LICENSE
Requires-Dist: numpy
Requires-Dist: scipy
Requires-Dist: matplotlib
Requires-Dist: numba
